adabelief_tf/AdaBelief_tf.py
adabelief_tf/__init__.py
ocrd_fork_adabelief_tf-0.2.1.dist-info/LICENSE.txt
ocrd_fork_adabelief_tf-0.2.1.dist-info/METADATA
ocrd_fork_adabelief_tf-0.2.1.dist-info/WHEEL
ocrd_fork_adabelief_tf-0.2.1.dist-info/top_level.txt
ocrd_fork_adabelief_tf-0.2.1.dist-info/RECORD
